loozr_sdk/__init__.py
loozr_sdk/accounts.py
loozr_sdk/creator_coin.py
loozr_sdk/utils/__init__.py
loozr_sdk/utils/account.py
loozr_sdk/utils/constants.py
loozr_sdk/utils/exceptions.py
loozr_sdk/utils/format.py
loozr_sdk/utils/rpc.py
loozr_sdk-1.0.1.dist-info/LICENSE
loozr_sdk-1.0.1.dist-info/METADATA
loozr_sdk-1.0.1.dist-info/WHEEL
loozr_sdk-1.0.1.dist-info/top_level.txt
loozr_sdk-1.0.1.dist-info/RECORD
